augment/__init__.py
augment/__main__.py
nlp_augment-1.0.9.dist-info/LICENSE
nlp_augment-1.0.9.dist-info/METADATA
nlp_augment-1.0.9.dist-info/WHEEL
nlp_augment-1.0.9.dist-info/top_level.txt
nlp_augment-1.0.9.dist-info/RECORD
