Metadata-Version: 2.1
Name: nlp-augment
Version: 1.0.9
Summary: It takes an sentence as an input and augment it
Home-page: https://github.com/saroarjahan/nlp-augment
Author: Md Saroar Jahan
Author-email: mjahan18@edu.oulu.fi
License: MIT
Platform: UNKNOWN
Classifier: License :: OSI Approved :: MIT License
Classifier: Programming Language :: Python :: 3.6
Classifier: Programming Language :: Python :: 3.7
Classifier: Programming Language :: Python :: 3.8
Requires-Dist: wn (==0.0.23)
Requires-Dist: wordnet (==0.0.1b2)
Requires-Dist: pywsd (==1.2.4)
Requires-Dist: nltk (==3.6.1)
